LICENSE
MANIFEST.in
README.md
setup.py
fpkws/KWS.py
fpkws/WideResNet12WithEMA.pth
fpkws/__init__.py
fpkws.egg-info/PKG-INFO
fpkws.egg-info/SOURCES.txt
fpkws.egg-info/dependency_links.txt
fpkws.egg-info/top_level.txt