Metadata-Version: 2.1
Name: fpkws
Version: 0.0.5
Summary: Spotting keywords in audio files
Author: FanPars
License-File: LICENSE
